MANIFEST.in
README.rst
setup.py
spm/__init__.py
spm.egg-info/PKG-INFO
spm.egg-info/SOURCES.txt
spm.egg-info/dependency_links.txt
spm.egg-info/requires.txt
spm.egg-info/top_level.txt